easy_pdf/__init__.py
easy_pdf/apps.py
easy_pdf/exceptions.py
easy_pdf/models.py
easy_pdf/rendering.py
easy_pdf/tests.py
easy_pdf/views.py
easy_pdf/templates/easy_pdf/base.html
django3_easy_pdf-0.1.2.dev1.dist-info/LICENSE
django3_easy_pdf-0.1.2.dev1.dist-info/METADATA
django3_easy_pdf-0.1.2.dev1.dist-info/WHEEL
django3_easy_pdf-0.1.2.dev1.dist-info/top_level.txt
django3_easy_pdf-0.1.2.dev1.dist-info/RECORD
