Metadata-Version: 1.1
Name: django3-easy-pdf
Version: 0.1.2.dev1
Summary: Django PDF views, the easy way
Home-page: https://github.com/meneses-pt/django3-easy-pdf
Author: Filip Wasilewski
Author-email: en@ig.ma
License: MIT
Keywords: django3-easy-pdf
Platform: UNKNOWN
Classifier: Development Status :: 4 - Beta
Classifier: Environment :: Web Environment
Classifier: Framework :: Django
Classifier: Intended Audience :: Developers
Classifier: License :: OSI Approved :: MIT License
Classifier: Operating System :: OS Independent
Classifier: Natural Language :: English
Classifier: Programming Language :: Python :: 2
Classifier: Programming Language :: Python :: 2.7
Classifier: Programming Language :: Python :: 3
Classifier: Programming Language :: Python :: 3.4
Classifier: Programming Language :: Python :: 3.5
Classifier: Programming Language :: Python :: 3.6
Classifier: Topic :: Software Development :: Libraries :: Python Modules
